pyzaplineplus/__init__.py
pyzaplineplus/core.py
pyzaplineplus/noise_detection.py
pyzaplineplus/py.typed
pyzaplineplus-0.1.0.dist-info/licenses/LICENSE
pyzaplineplus-0.1.0.dist-info/METADATA
pyzaplineplus-0.1.0.dist-info/WHEEL
pyzaplineplus-0.1.0.dist-info/top_level.txt
pyzaplineplus-0.1.0.dist-info/RECORD
