Metadata-Version: 2.4
Name: pyzaplineplus
Version: 0.1.0
Summary: Adaptive removal of spectral line-noise in EEG via DSS (Zapline-plus reimplementation).
Author-email: Sina Esmaeili <sina.esmaeili@umontreal.ca>
License: MIT License
Project-URL: Homepage, https://github.com/snesmaeili/PyZapline_plus
Project-URL: Documentation, https://snesmaeili.github.io/PyZapline_plus/
Project-URL: Source, https://github.com/snesmaeili/PyZapline_plus
Project-URL: Issues, https://github.com/snesmaeili/PyZapline_plus/issues
Keywords: EEG,MEG,BCI,DSS,line noise,zapline
Classifier: Development Status :: 3 - Alpha
Classifier: Intended Audience :: Science/Research
Classifier: Programming Language :: Python :: 3 :: Only
Classifier: Programming Language :: Python :: 3.8
Classifier: Programming Language :: Python :: 3.9
Classifier: Programming Language :: Python :: 3.10
Classifier: Programming Language :: Python :: 3.11
Classifier: Programming Language :: Python :: 3.12
Classifier: Programming Language :: Python :: 3.13
Classifier: Topic :: Scientific/Engineering :: Information Analysis
Requires-Python: >=3.8
License-File: LICENSE
Requires-Dist: numpy>=1.22
Requires-Dist: scipy>=1.8
Requires-Dist: scikit-learn>=1.1
Requires-Dist: matplotlib>=3.5
Provides-Extra: mne
Requires-Dist: mne>=1.0; extra == "mne"
Provides-Extra: dev
Requires-Dist: pytest>=8; extra == "dev"
Requires-Dist: pytest-cov>=5; extra == "dev"
Requires-Dist: ruff>=0.5; extra == "dev"
Requires-Dist: mypy>=1.10; extra == "dev"
Requires-Dist: build>=1.2; extra == "dev"
Requires-Dist: twine>=5.1; extra == "dev"
Requires-Dist: check-manifest>=0.49; extra == "dev"
Requires-Dist: mkdocs>=1.6; extra == "dev"
Requires-Dist: mkdocs-material>=9.5; extra == "dev"
Requires-Dist: mkdocstrings[python]>=0.24; extra == "dev"
Dynamic: license-file
